chemrxiv/__init__.py
chemrxiv/author.py
chemrxiv/category.py
chemrxiv/client.py
chemrxiv/exceptions.py
chemrxiv/license.py
chemrxiv/result.py
chemrxiv/search.py
chemrxiv/sort.py
chemrxiv-0.1.2.dist-info/METADATA
chemrxiv-0.1.2.dist-info/WHEEL
chemrxiv-0.1.2.dist-info/licenses/LICENSE
chemrxiv-0.1.2.dist-info/RECORD
